{
  "cta": {
    "type": {
      "description": "Write description.",
      "value": "standard",
      "type": "string"
    },
    "default": {
      "color": {
        "value": "{ theme.color.lightest.value }"
      },
      "background": {
        "color": {
          "value": "{ theme.color.darkest.value }"
        }
      },
      "gap": {
        "value": "{ theme.spacer.md.value }"
      },
      "padding": {
        "block": {
          "value": "{ theme.spacer.sm.value }"
        },
        "inline": {
          "value": "{ theme.spacer.md.value }"
        }
      },
      "border": {
        "color": {
          "value": "{ cta.default.background.color.value }"
        }
      }
    },
    "loading": {
      "message": {
        "description": "Write description.",
        "value": "Loading...",
        "type": "string"
      },
      "icon": {
        "name": {
          "description": "Write description.",
          "value": "spinner",
          "type": "string"
        }
      },
      "background": {
        "color": {
          "value": "{ theme.color.darkest.value}"
        }
      },
      "border": {
        "color": {
          "value": "{ cta.loading.background.color.value }"
        }
      }
    },
    "icon": {
      "name": {
        "description": "Write description.",
        "value": "arrow-right",
        "type": "string"
      },
      "position": {
        "description": "Write description.",
        "value": "end",
        "type": "string"
      }
    },
    "font": {
      "family": {
        "description": "Write description.",
        "value": "{ theme.font.family.default.value }"
      }
    },
    "hover": {
      "background": {
        "color": {
          "value": "{ theme.color.darkest.value}"
        }
      },
      "border": {
        "color": {
          "value": "{ cta.hover.background.color.value }"
        }
      }
    },
    "focus": {
      "outline": {
        "color": {
          "value": "{ theme.color.focus.value }"
        }
      }
    },
    "active": {
      "background": {
        "color": {
          "value": "{ theme.color.primary.value }"
        }
      },
      "border": {
        "color": {
          "value": "{ cta.active.background.color.value }"
        }
      }
    },
    "disabled": {
      "background": {
        "color": {
          "value": "{ theme.color.disabled.value }"
        }
      },
      "border": {
        "color": {
          "value": "{ cta.disabled.background.color.value }"
        }
      }

    }
  }
}
